{
  "metadata": {
    "repo_path": "https://gitcode.com/boostkit/kpglibc.git",
    "start_time": "2026-06-25T11:03:00Z",
    "end_time": "2026-06-25T11:07:00Z",
    "duration_seconds": 240,
    "total_steps": 8,
    "verification_mode": "remote_host",
    "remote_host": {
      "host": "173.48.5.2",
      "user": "root",
      "repo_path": "/root/workspace/kpglibc"
    }
  },
  "machine_spec": {
    "host_machine": {
      "architecture": "aarch64",
      "cpu_model": "йІІй№Ҹ920",
      "cpu_cores": 96,
      "memory": "502Gi",
      "disk": "1.1T",
      "docker_version": "Docker version 18.09.0"
    },
    "container": {
      "os": "openEuler 24.03 LTS",
      "architecture": "aarch64",
      "cpu_cores": 96,
      "memory": "502Gi"
    },
    "image_source": {
      "type": "base_image",
      "image_name": "hub.oepkgs.net/openeuler/openeuler:24.03-lts",
      "selection_reason": "ж–ҮжЎЈжҺЁиҚҗopenEuler 22.03/24.03 LTS вҶ’ дҪҝз”ЁopenEuler 24.03 LTSй•ңеғҸ"
    }
  },
  "document_reading_summary": {
    "architecture": {
      "value": "aarch64пјҲйІІй№Ҹ920ж–°еһӢеҸ·/950еӨ„зҗҶеҷЁпјү",
      "source": "docs/zh/installation_guide.md - е·ІйӘҢиҜҒзҺҜеўғз« иҠӮ"
    },
    "recommended_image": {
      "value": "openEuler 22.03 LTS SP3/openEuler 24.03 LTS SP2",
      "source": "docs/zh/installation_guide.md - е·ІйӘҢиҜҒзҺҜеўғз« иҠӮ"
    },
    "dependencies": {
      "value": [
        "GCC 10.3.1жҲ–GCC 12.3.1",
        "cmake",
        "make"
      ],
      "source": "docs/zh/installation_guide.md - е·ІйӘҢиҜҒзҺҜеўғз« иҠӮ"
    },
    "build_commands": {
      "value": "cd kpglibc && sh build.sh",
      "source": "docs/zh/installation_guide.md - зј–иҜ‘е®үиЈ…жӯҘйӘӨ"
    },
    "ut_commands": {
      "value": "ж–ҮжЎЈжңӘжҸҗдҫӣеҚ•е…ғжөӢиҜ•е‘Ҫд»Ө",
      "source": "жңӘжүҫеҲ°"
    },
    "sample_commands": {
      "value": "LD_PRELOAD=/xxx/output/libkpglibc.so <зЁӢеәҸ> жҲ– gcc -L/xxx/output -lkpglibc",
      "source": "docs/zh/quick_start.md - дҪҝз”Ёж–№ејҸз« иҠӮ"
    },
    "special_dependencies": {
      "value": [],
      "source": "жңӘжүҫеҲ°зү№ж®Ҡдҫқиө–пјҲCANNзӯүпјү"
    }
  },
  "execution_log": [
    {
      "timestamp": "2026-06-25T11:03:00Z",
      "command": "git clone https://gitcode.com/boostkit/kpglibc.git",
      "success": true,
      "output": "д»“еә“е…ӢйҡҶжҲҗеҠҹ",
      "error": "",
      "returncode": 0
    },
    {
      "timestamp": "2026-06-25T11:04:00Z",
      "command": "dnf install -y gcc gcc-c++ cmake make",
      "success": true,
      "output": "дҫқиө–е®үиЈ…жҲҗеҠҹпјҲ21дёӘеҢ…пјү",
      "error": "",
      "returncode": 0
    },
    {
      "timestamp": "2026-06-25T11:05:00Z",
      "command": "cd /workspace/kpglibc && sh build.sh",
      "success": true,
      "output": "жһ„е»әжҲҗеҠҹпјҲз”ҹжҲҗ4дёӘ.soж–Үд»¶пјү",
      "error": "",
      "returncode": 0,
      "duration_seconds": 1
    },
    {
      "timestamp": "2026-06-25T11:06:00Z",
      "command": "ls -la output",
      "success": true,
      "output": "йӘҢиҜҒoutputзӣ®еҪ•еӯҳеңЁ4дёӘ.soж–Үд»¶",
      "error": "",
      "returncode": 0
    }
  ],
  "process_timeline": [
    {
      "timestamp": "2026-06-25T11:03:00Z",
      "step": "start",
      "action": "йӘҢиҜҒиҝҮзЁӢеҗҜеҠЁ",
      "result": "started"
    },
    {
      "timestamp": "2026-06-25T11:03:00Z",
      "step": "clone_repo",
      "action": "е…ӢйҡҶboostkit/kpglibcд»“еә“",
      "result": "success"
    },
    {
      "timestamp": "2026-06-25T11:04:00Z",
      "step": "read_docs",
      "action": "йҳ…иҜ»READMEе’Ңе®үиЈ…жҢҮеҚ—",
      "result": "success"
    },
    {
      "timestamp": "2026-06-25T11:04:00Z",
      "step": "start_container",
      "action": "еҗҜеҠЁopenEulerе®№еҷЁ",
      "result": "success"
    },
    {
      "timestamp": "2026-06-25T11:05:00Z",
      "step": "install_deps",
      "action": "е®үиЈ…дҫқиө–еҢ…",
      "result": "success"
    },
    {
      "timestamp": "2026-06-25T11:05:00Z",
      "step": "build",
      "action": "жү§иЎҢsh build.sh",
      "result": "success"
    },
    {
      "timestamp": "2026-06-25T11:06:00Z",
      "step": "verify",
      "action": "йӘҢиҜҒжһ„е»әдә§зү©",
      "result": "success"
    },
    {
      "timestamp": "2026-06-25T11:07:00Z",
      "step": "cleanup",
      "action": "жё…зҗҶе®№еҷЁ",
      "result": "success"
    }
  ],
  "final_results": {
    "build": {
      "status": "success",
      "duration_seconds": 1,
      "artifacts": [
        {
          "name": "libkpglibc_neon.so",
          "path": "/workspace/kpglibc/output/libkpglibc_neon.so",
          "size": "67KB"
        },
        {
          "name": "libkpglibc_sve.so",
          "path": "/workspace/kpglibc/output/libkpglibc_sve.so",
          "size": "67KB"
        },
        {
          "name": "libkpglibc_sve_950.so",
          "path": "/workspace/kpglibc/output/libkpglibc_sve_950.so",
          "size": "67KB"
        },
        {
          "name": "libkpglibc_time.so",
          "path": "/workspace/kpglibc/output/libkpglibc_time.so",
          "size": "67KB"
        }
      ]
    },
    "ut": {
      "status": "not_run",
      "reason": "ж–ҮжЎЈжңӘжҸҗдҫӣеҚ•е…ғжөӢиҜ•жү§иЎҢе‘Ҫд»ӨпјҢbuild.shи„ҡжң¬жңӘеҢ…еҗ«жөӢиҜ•жӯҘйӘӨ"
    },
    "sample": {
      "status": "not_run",
      "reason": "ж–ҮжЎЈжңӘжҸҗдҫӣж ·дҫӢзЁӢеәҸпјҢйңҖиҰҒз”ЁжҲ·иҮӘиЎҢзј–еҶҷжөӢиҜ•зЁӢеәҸе№¶дҪҝз”ЁLD_PRELOADжҲ–gccй“ҫжҺҘж–№ејҸйӘҢиҜҒ"
    }
  },
  "documentation_gaps": [
    "жңӘжҸҗдҫӣеҚ•е…ғжөӢиҜ•жү§иЎҢе‘Ҫд»ӨжҲ–жөӢиҜ•зЁӢеәҸ",
    "жңӘжҸҗдҫӣж ·дҫӢйӘҢиҜҒзЁӢеәҸ",
    "build.shи„ҡжң¬жңӘеҢ…еҗ«жөӢиҜ•зј–иҜ‘жӯҘйӘӨ"
  ],
  "problems_encountered": []
}